__init__.py
magicfeedback.py
MagicFeeedback-0.0.1.dist-info/LICENCE
MagicFeeedback-0.0.1.dist-info/METADATA
MagicFeeedback-0.0.1.dist-info/WHEEL
MagicFeeedback-0.0.1.dist-info/top_level.txt
MagicFeeedback-0.0.1.dist-info/RECORD
